spectrometer_reading_plugin/__init__.py
spectrometer_reading_plugin/additional_config.ini
spectrometer_reading_plugin/additional_sql.sql
spectrometer_reading_plugin/post_install.sh
spectrometer_reading_plugin/exportable_datasets/as7341_spectrum_readings.yaml
spectrometer_reading_plugin/exportable_datasets/as7341_spectrum_readings_415.yaml
spectrometer_reading_plugin/exportable_datasets/as7341_spectrum_readings_445.yaml
spectrometer_reading_plugin/exportable_datasets/as7341_spectrum_readings_480.yaml
spectrometer_reading_plugin/exportable_datasets/as7341_spectrum_readings_515.yaml
spectrometer_reading_plugin/exportable_datasets/as7341_spectrum_readings_555.yaml
spectrometer_reading_plugin/exportable_datasets/as7341_spectrum_readings_590.yaml
spectrometer_reading_plugin/exportable_datasets/as7341_spectrum_readings_630.yaml
spectrometer_reading_plugin/exportable_datasets/as7341_spectrum_readings_680.yaml
spectrometer_reading_plugin/ui/contrib/charts/spec_415.yaml
spectrometer_reading_plugin/ui/contrib/charts/spec_445.yaml
spectrometer_reading_plugin/ui/contrib/charts/spec_480.yaml
spectrometer_reading_plugin/ui/contrib/charts/spec_515.yaml
spectrometer_reading_plugin/ui/contrib/charts/spec_555.yaml
spectrometer_reading_plugin/ui/contrib/charts/spec_590.yaml
spectrometer_reading_plugin/ui/contrib/charts/spec_630.yaml
spectrometer_reading_plugin/ui/contrib/charts/spec_680.yaml
spectrometer_reading_plugin/ui/contrib/jobs/spectrometer_reading.yaml
spectrometer_reading_plugin-0.3.2.dist-info/licenses/LICENSE.txt
spectrometer_reading_plugin-0.3.2.dist-info/METADATA
spectrometer_reading_plugin-0.3.2.dist-info/WHEEL
spectrometer_reading_plugin-0.3.2.dist-info/entry_points.txt
spectrometer_reading_plugin-0.3.2.dist-info/top_level.txt
spectrometer_reading_plugin-0.3.2.dist-info/RECORD
