Metadata-Version: 2.4
Name: spectrometer-reading-plugin
Version: 0.3.2
Summary: Take spectrometer readings (between OD readings) from the Adafruit AS7341 attached to your Pioreactor
Home-page: https://github.com/Pioreactor/spectrometer-reading-plugin
Author: Kelly Tran, Cameron Davidson-Pilon, Pioreactor
Author-email: info@pioreactor.com
License: MIT
License-File: LICENSE.txt
Requires-Dist: adafruit-circuitpython-as7341
Dynamic: author
Dynamic: author-email
Dynamic: description
Dynamic: description-content-type
Dynamic: home-page
Dynamic: license
Dynamic: license-file
Dynamic: requires-dist
Dynamic: summary
